wowool/lingware/build/build.py
wowool/lingware/build/git.py
wowool/lingware/build/pytask.py
wowool/lingware/build/templates.py
wowool/lingware/build/utilities.py
wowool/lingware/build/domain/__init__.py
wowool/lingware/build/domain/build.py
wowool/lingware/build/domain/templates.py
wowool/lingware/build/language/__init__.py
wowool/lingware/build/language/build.py
wowool/lingware/build/language/templates.py
wowool/lingware/build/lid/__init__.py
wowool/lingware/build/lid/build.py
wowool/lingware/build/lid/templates.py
wowool/lingware/build/tools/afst/__main__.py
wowool/lingware/build/tools/convert_domain_info/__init__.py
wowool/lingware/build/tools/convert_domain_info/__main__.py
wowool/lingware/build/tools/convert_domain_info/convert.py
wowool/lingware/build/tools/convert_language_info/__main__.py
wowool/lingware/unittest/__init__.py
wowool/lingware/unittest/unittest.py
wowool_lingware_build-1.1.4.dev1.dist-info/METADATA
wowool_lingware_build-1.1.4.dev1.dist-info/WHEEL
wowool_lingware_build-1.1.4.dev1.dist-info/entry_points.txt
wowool_lingware_build-1.1.4.dev1.dist-info/top_level.txt
wowool_lingware_build-1.1.4.dev1.dist-info/RECORD
